{"openapi":"3.1.0","info":{"title":"Decision Service","version":"0.1.0"},"paths":{"/api/v1/config/decisions":{"get":{"tags":["Decision","Configuration"],"summary":"List Decisions","description":"Returns the list of available decisions.","operationId":"list_decisions_api_v1_config_decisions_get","responses":{"200":{"description":"Successful Response","content":{"application/json":{"schema":{}}}}}},"post":{"tags":["Decision","Configuration"],"summary":"Add Decision","description":"Adds a decision to the runtime and persists to database.","operationId":"add_decision_api_v1_config_decisions_post","requestBody":{"content":{"application/json":{"schema":{"$ref":"#/components/schemas/DecisionEntry"}}},"required":true},"responses":{"200":{"description":"Successful Response","content":{"application/json":{"schema":{}}}},"422":{"description":"Validation Error","content":{"application/json":{"schema":{"$ref":"#/components/schemas/HTTPValidationError"}}}}}}},"/api/v1/config/blacklist":{"get":{"tags":["Decision","Configuration"],"summary":"Get Blacklist","description":"Returns the current blacklist.","operationId":"get_blacklist_api_v1_config_blacklist_get","responses":{"200":{"description":"Successful Response","content":{"application/json":{"schema":{}}}}}},"post":{"tags":["Decision","Configuration"],"summary":"Add To Blacklist","description":"Adds a decision to the blacklist and persists to database.","operationId":"add_to_blacklist_api_v1_config_blacklist_post","requestBody":{"content":{"application/json":{"schema":{"$ref":"#/components/schemas/BlacklistEntry"}}},"required":true},"responses":{"200":{"description":"Successful Response","content":{"application/json":{"schema":{}}}},"422":{"description":"Validation Error","content":{"application/json":{"schema":{"$ref":"#/components/schemas/HTTPValidationError"}}}}}}},"/api/v1/config/decisions/{name}":{"delete":{"tags":["Decision","Configuration"],"summary":"Remove Decision","description":"Removes a decision from the runtime and database.","operationId":"remove_decision_api_v1_config_decisions__name__delete","parameters":[{"name":"name","in":"path","required":true,"schema":{"type":"string","title":"Name"}}],"responses":{"200":{"description":"Successful Response","content":{"application/json":{"schema":{}}}},"422":{"description":"Validation Error","content":{"application/json":{"schema":{"$ref":"#/components/schemas/HTTPValidationError"}}}}}}},"/api/v1/config/blacklist/{name}":{"delete":{"tags":["Decision","Configuration"],"summary":"Remove From Blacklist","description":"Removes a decision from the blacklist and database.","operationId":"remove_from_blacklist_api_v1_config_blacklist__name__delete","parameters":[{"name":"name","in":"path","required":true,"schema":{"type":"string","title":"Name"}}],"responses":{"200":{"description":"Successful Response","content":{"application/json":{"schema":{}}}},"422":{"description":"Validation Error","content":{"application/json":{"schema":{"$ref":"#/components/schemas/HTTPValidationError"}}}}}}},"/api/v1/config/risk-levels":{"get":{"tags":["Risk Levels","Configuration"],"summary":"List Risk Levels","description":"Returns the list of available risk levels.","operationId":"list_risk_levels_api_v1_config_risk_levels_get","responses":{"200":{"description":"Successful Response","content":{"application/json":{"schema":{}}}}}},"post":{"tags":["Risk Levels","Configuration"],"summary":"Add Risk Level","description":"Adds a risk level to the runtime and persists to database.","operationId":"add_risk_level_api_v1_config_risk_levels_post","requestBody":{"content":{"application/json":{"schema":{"$ref":"#/components/schemas/RiskLevelEntry"}}},"required":true},"responses":{"200":{"description":"Successful Response","content":{"application/json":{"schema":{}}}},"422":{"description":"Validation Error","content":{"application/json":{"schema":{"$ref":"#/components/schemas/HTTPValidationError"}}}}}}},"/api/v1/config/risk-levels/{name}":{"delete":{"tags":["Risk Levels","Configuration"],"summary":"Remove Risk Level","description":"Removes a risk level from the runtime and database.","operationId":"remove_risk_level_api_v1_config_risk_levels__name__delete","parameters":[{"name":"name","in":"path","required":true,"schema":{"type":"string","title":"Name"}}],"responses":{"200":{"description":"Successful Response","content":{"application/json":{"schema":{}}}},"422":{"description":"Validation Error","content":{"application/json":{"schema":{"$ref":"#/components/schemas/HTTPValidationError"}}}}}}},"/api/v1/subscriptions":{"get":{"tags":["Subscriptions"],"summary":"List Subscriptions","description":"Returns all active subscriptions.","operationId":"list_subscriptions_api_v1_subscriptions_get","responses":{"200":{"description":"Successful Response","content":{"application/json":{"schema":{}}}}}},"post":{"tags":["Subscriptions"],"summary":"Create Subscription","description":"Creates a new subscription.","operationId":"create_subscription_api_v1_subscriptions_post","requestBody":{"content":{"application/json":{"schema":{"$ref":"#/components/schemas/SubscriptionEntry"}}},"required":true},"responses":{"201":{"description":"Successful Response","content":{"application/json":{"schema":{}}}},"422":{"description":"Validation Error","content":{"application/json":{"schema":{"$ref":"#/components/schemas/HTTPValidationError"}}}}}}},"/api/v1/subscriptions/{subscription_id}":{"get":{"tags":["Subscriptions"],"summary":"Get Subscription","description":"Returns a specific subscription by ID.","operationId":"get_subscription_api_v1_subscriptions__subscription_id__get","parameters":[{"name":"subscription_id","in":"path","required":true,"schema":{"type":"string","title":"Subscription Id"}}],"responses":{"200":{"description":"Successful Response","content":{"application/json":{"schema":{}}}},"422":{"description":"Validation Error","content":{"application/json":{"schema":{"$ref":"#/components/schemas/HTTPValidationError"}}}}}},"delete":{"tags":["Subscriptions"],"summary":"Delete Subscription","description":"Deletes a subscription by ID.","operationId":"delete_subscription_api_v1_subscriptions__subscription_id__delete","parameters":[{"name":"subscription_id","in":"path","required":true,"schema":{"type":"string","title":"Subscription Id"}}],"responses":{"200":{"description":"Successful Response","content":{"application/json":{"schema":{}}}},"422":{"description":"Validation Error","content":{"application/json":{"schema":{"$ref":"#/components/schemas/HTTPValidationError"}}}}}}},"/health":{"get":{"summary":"Health","description":"Health check endpoint.","operationId":"health_health_get","responses":{"200":{"description":"Successful Response","content":{"application/json":{"schema":{}}}}}}}},"components":{"schemas":{"BlacklistEntry":{"properties":{"name":{"type":"string","title":"Name"},"reason":{"anyOf":[{"type":"string"},{"type":"null"}],"title":"Reason"}},"type":"object","required":["name"],"title":"BlacklistEntry","description":"Represents a blacklisted decision."},"DecisionEntry":{"properties":{"name":{"type":"string","title":"Name"},"description":{"anyOf":[{"type":"string"},{"type":"null"}],"title":"Description"},"risk_level_id":{"anyOf":[{"type":"integer"},{"type":"null"}],"title":"Risk Level Id"},"justification":{"anyOf":[{"type":"string"},{"type":"null"}],"title":"Justification"}},"type":"object","required":["name"],"title":"DecisionEntry","description":"Represents a decision in the system."},"HTTPValidationError":{"properties":{"detail":{"items":{"$ref":"#/components/schemas/ValidationError"},"type":"array","title":"Detail"}},"type":"object","title":"HTTPValidationError"},"RiskLevelEntry":{"properties":{"name":{"type":"string","title":"Name"},"degree":{"type":"integer","title":"Degree"},"description":{"anyOf":[{"type":"string"},{"type":"null"}],"title":"Description"}},"type":"object","required":["name","degree"],"title":"RiskLevelEntry","description":"Represents a risk level in the system."},"SubscriptionEntry":{"properties":{"id":{"anyOf":[{"type":"string"},{"type":"null"}],"title":"Id"},"callback_url":{"type":"string","title":"Callback Url"},"cell_ids":{"items":{"type":"integer"},"type":"array","title":"Cell Ids"},"event_types":{"items":{"type":"string"},"type":"array","title":"Event Types"},"created_at":{"anyOf":[{"type":"string","format":"date-time"},{"type":"null"}],"title":"Created At"}},"type":"object","required":["callback_url","cell_ids","event_types"],"title":"SubscriptionEntry","description":"Represents a subscription to cell events."},"ValidationError":{"properties":{"loc":{"items":{"anyOf":[{"type":"string"},{"type":"integer"}]},"type":"array","title":"Location"},"msg":{"type":"string","title":"Message"},"type":{"type":"string","title":"Error Type"},"input":{"title":"Input"},"ctx":{"type":"object","title":"Context"}},"type":"object","required":["loc","msg","type"],"title":"ValidationError"}}}}